{"_ts":[1493196703,1493196721,1493210031,1493215671],"_r":{"breakdown":{"html":{"bytes":[253930,260672,239064,237176],"requests":[14,14,12,12]},"js":{"bytes":[554048,554021,553882,553830],"requests":[28,28,27,27]},"css":{"bytes":[220752,220766,220767,220766],"requests":[3,3,3,3]},"image":{"bytes":[8767331,21047853,20396323,21173980],"requests":[146,270,270,270]},"flash":{"bytes":[0,0,0,0],"requests":[0,0,0,0]},"font":{"bytes":[439299,439299,439300,439299],"requests":[4,4,4,4]},"other":{"bytes":[82317,12237997,8320745,22422870],"requests":[6,17,18,14]}},"date":[1493196703,1493196721,1493210031,1493215671],"domElements":[3569,3569,3568,3568],"domInteractive":[6265,9656,6099,5575],"firstPaint":[6240,11027,5939,4771],"fullyLoaded":[36158,78286,75913,80131],"id":["170426_6J_NFD","170426_5X_ND5","170426_MZ_ZVE","170426_B0_1451"],"loadTime":[34098,61135,63346,49788],"render":[6496,11607,6396,5095],"SpeedIndex":[6709,26605,22665,15602],"TTFB":[306,4325,1293,327],"videoFrames":[[{"_i":"frame_0000.jpg","_t":0,"_vc":0},{"_i":"frame_0065.jpg","_t":6500,"_vc":81},{"_i":"frame_0076.jpg","_t":7600,"_vc":100}],[{"_i":"frame_0000.jpg","_t":0,"_vc":0},{"_i":"frame_0116.jpg","_t":11600,"_vc":71},{"_i":"frame_0622.jpg","_t":62200,"_vc":74},{"_i":"frame_0628.jpg","_t":62800,"_vc":100},{"_i":"frame_0633.jpg","_t":63300,"_vc":100},{"_i":"frame_0639.jpg","_t":63900,"_vc":99},{"_i":"frame_0644.jpg","_t":64400,"_vc":99},{"_i":"frame_0649.jpg","_t":64900,"_vc":99},{"_i":"frame_0655.jpg","_t":65500,"_vc":99},{"_i":"frame_0780.jpg","_t":78000,"_vc":99},{"_i":"frame_0786.jpg","_t":78600,"_vc":99},{"_i":"frame_0792.jpg","_t":79200,"_vc":99},{"_i":"frame_0797.jpg","_t":79700,"_vc":100},{"_i":"frame_0803.jpg","_t":80300,"_vc":100},{"_i":"frame_0809.jpg","_t":80900,"_vc":99},{"_i":"frame_0815.jpg","_t":81500,"_vc":99},{"_i":"frame_0821.jpg","_t":82100,"_vc":99},{"_i":"frame_0826.jpg","_t":82600,"_vc":100},{"_i":"frame_0830.jpg","_t":83000,"_vc":100}],[{"_i":"frame_0000.jpg","_t":0,"_vc":0},{"_i":"frame_0064.jpg","_t":6400,"_vc":52},{"_i":"frame_0078.jpg","_t":7800,"_vc":69},{"_i":"frame_0083.jpg","_t":8300,"_vc":69},{"_i":"frame_0091.jpg","_t":9100,"_vc":69},{"_i":"frame_0097.jpg","_t":9700,"_vc":71},{"_i":"frame_0608.jpg","_t":60800,"_vc":99},{"_i":"frame_0751.jpg","_t":75100,"_vc":99},{"_i":"frame_0756.jpg","_t":75600,"_vc":99},{"_i":"frame_0762.jpg","_t":76200,"_vc":100},{"_i":"frame_0767.jpg","_t":76700,"_vc":99},{"_i":"frame_0773.jpg","_t":77300,"_vc":99},{"_i":"frame_0778.jpg","_t":77800,"_vc":99},{"_i":"frame_0783.jpg","_t":78300,"_vc":99},{"_i":"frame_0789.jpg","_t":78900,"_vc":99},{"_i":"frame_0795.jpg","_t":79500,"_vc":99},{"_i":"frame_0798.jpg","_t":79800,"_vc":100}],[{"_i":"frame_0000.jpg","_t":0,"_vc":0},{"_i":"frame_0051.jpg","_t":5100,"_vc":55},{"_i":"frame_0055.jpg","_t":5500,"_vc":55},{"_i":"frame_0067.jpg","_t":6700,"_vc":71},{"_i":"frame_0389.jpg","_t":38900,"_vc":99},{"_i":"frame_0394.jpg","_t":39400,"_vc":99},{"_i":"frame_0405.jpg","_t":40500,"_vc":100},{"_i":"frame_0410.jpg","_t":41000,"_vc":99},{"_i":"frame_0415.jpg","_t":41500,"_vc":99},{"_i":"frame_0444.jpg","_t":44400,"_vc":99},{"_i":"frame_0450.jpg","_t":45000,"_vc":99},{"_i":"frame_0461.jpg","_t":46100,"_vc":99},{"_i":"frame_0472.jpg","_t":47200,"_vc":99},{"_i":"frame_0477.jpg","_t":47700,"_vc":99},{"_i":"frame_0488.jpg","_t":48800,"_vc":99},{"_i":"frame_0493.jpg","_t":49300,"_vc":98},{"_i":"frame_0499.jpg","_t":49900,"_vc":98},{"_i":"frame_0505.jpg","_t":50500,"_vc":98},{"_i":"frame_0511.jpg","_t":51100,"_vc":99},{"_i":"frame_0517.jpg","_t":51700,"_vc":100},{"_i":"frame_0523.jpg","_t":52300,"_vc":99},{"_i":"frame_0528.jpg","_t":52800,"_vc":99},{"_i":"frame_0533.jpg","_t":53300,"_vc":98},{"_i":"frame_0538.jpg","_t":53800,"_vc":99},{"_i":"frame_0544.jpg","_t":54400,"_vc":99},{"_i":"frame_0550.jpg","_t":55000,"_vc":99},{"_i":"frame_0555.jpg","_t":55500,"_vc":99},{"_i":"frame_0560.jpg","_t":56000,"_vc":99},{"_i":"frame_0565.jpg","_t":56500,"_vc":98},{"_i":"frame_0571.jpg","_t":57100,"_vc":99},{"_i":"frame_0577.jpg","_t":57700,"_vc":100},{"_i":"frame_0583.jpg","_t":58300,"_vc":99},{"_i":"frame_0588.jpg","_t":58800,"_vc":99},{"_i":"frame_0593.jpg","_t":59300,"_vc":99},{"_i":"frame_0599.jpg","_t":59900,"_vc":99},{"_i":"frame_0604.jpg","_t":60400,"_vc":99},{"_i":"frame_0609.jpg","_t":60900,"_vc":99},{"_i":"frame_0615.jpg","_t":61500,"_vc":99},{"_i":"frame_0620.jpg","_t":62000,"_vc":99},{"_i":"frame_0626.jpg","_t":62600,"_vc":98},{"_i":"frame_0631.jpg","_t":63100,"_vc":99},{"_i":"frame_0636.jpg","_t":63600,"_vc":99},{"_i":"frame_0641.jpg","_t":64100,"_vc":99},{"_i":"frame_0647.jpg","_t":64700,"_vc":99},{"_i":"frame_0653.jpg","_t":65300,"_vc":99},{"_i":"frame_0659.jpg","_t":65900,"_vc":99},{"_i":"frame_0665.jpg","_t":66500,"_vc":99},{"_i":"frame_0670.jpg","_t":67000,"_vc":100},{"_i":"frame_0675.jpg","_t":67500,"_vc":99},{"_i":"frame_0681.jpg","_t":68100,"_vc":99},{"_i":"frame_0686.jpg","_t":68600,"_vc":98},{"_i":"frame_0691.jpg","_t":69100,"_vc":99},{"_i":"frame_0697.jpg","_t":69700,"_vc":99},{"_i":"frame_0702.jpg","_t":70200,"_vc":99},{"_i":"frame_0707.jpg","_t":70700,"_vc":99},{"_i":"frame_0712.jpg","_t":71200,"_vc":99},{"_i":"frame_0718.jpg","_t":71800,"_vc":98},{"_i":"frame_0724.jpg","_t":72400,"_vc":99},{"_i":"frame_0730.jpg","_t":73000,"_vc":100},{"_i":"frame_0735.jpg","_t":73500,"_vc":99},{"_i":"frame_0741.jpg","_t":74100,"_vc":99},{"_i":"frame_0746.jpg","_t":74600,"_vc":99},{"_i":"frame_0751.jpg","_t":75100,"_vc":99},{"_i":"frame_0756.jpg","_t":75600,"_vc":99},{"_i":"frame_0761.jpg","_t":76100,"_vc":100},{"_i":"frame_0767.jpg","_t":76700,"_vc":99},{"_i":"frame_0772.jpg","_t":77200,"_vc":99},{"_i":"frame_0777.jpg","_t":77700,"_vc":99},{"_i":"frame_0783.jpg","_t":78300,"_vc":99},{"_i":"frame_0788.jpg","_t":78800,"_vc":99},{"_i":"frame_0793.jpg","_t":79300,"_vc":99},{"_i":"frame_0798.jpg","_t":79800,"_vc":99},{"_i":"frame_0804.jpg","_t":80400,"_vc":99},{"_i":"frame_0810.jpg","_t":81000,"_vc":99},{"_i":"frame_0816.jpg","_t":81600,"_vc":99},{"_i":"frame_0821.jpg","_t":82100,"_vc":100},{"_i":"frame_0823.jpg","_t":82300,"_vc":100}]],"visualComplete":[7600,62800,76200,40500],"lighthouse":[null,null,null,null],"pagespeed":[13,13,13,13]}}